{"实践_http接口自动化测试_创建一条完整的用例.md":"ySiPdM7f","index.md":"MDhv-c_X","实践_webui自动化测试_创建app工程.md":"CjZi8CzL","实践_webui自动化测试_创建一条完整的用例.md":"BnIC9N2M","实践_命令行自动化测试_创建app工程.md":"D_kgtz7h","实践_webui自动化测试_初始化项目.md":"_bQZJVxo","实践_命令行自动化测试_初始化项目.md":"tdi2GcCU","实践_dbus接口自动化测试_创建app工程.md":"Cx92clSO","实践_linux桌面ui自动化测试_创建一条完整的用例.md":"CiMjikum","指南_特色功能_数据回填.md":"Dkgozy54","指南_特色功能_全自动日志.md":"C9bnc6KB","指南_元素定位_图像识别.md":"B3HzDLp6","指南_特色功能_标签导出.md":"CrI0jH9G","指南_特色功能_重启类场景.md":"PtZUUg58","指南_特色功能_wayland适配.md":"DK1zZYKh","指南_特色功能_webui.md":"C7k_jLlu","实践_http接口自动化测试_初始化项目.md":"iIonBhki","实践_http接口自动化测试_创建app工程.md":"Cu-7v2nr","指南_简介_youqu是什么.md":"Mc03AeWu","指南_框架必备_测试报告.md":"CYhtrJW-","实践_dbus接口自动化测试_初始化项目.md":"BLAlR06e","contributing.md":"DNUJNhvG","指南_元素定位_ocr识别.md":"CaoBmN1z","指南_特色功能_标签自动同步.md":"YcPE9KWV","指南_特色功能_标签化管理.md":"DjDze7Ag","实践_linux桌面ui自动化测试_创建app工程.md":"BGu8_-Wu","实践_命令行自动化测试_创建一条完整的用例.md":"CCeRmXxY","规划_未来规划.md":"BLf0GvS7","规划_框架设计_at基础框架设计方案.md":"Dpf9k8u4","规划_框架设计_at应用库设计方案.md":"CQEmc4m7","规划_框架设计_自动化测试架构设计v1.0.md":"DQEGnrmf","指南_特色功能_远程交互式控制.md":"CwiB0Rvu","指南_环境_环境部署.md":"Bs-5VWcj","指南_特色功能_失败录屏.md":"CVTLorT7","release.md":"aLxBFUlh","指南_环境_全局配置.md":"DasbxOCz","指南_框架必备_执行管理器.md":"DseLtSrn","实践_linux桌面ui自动化测试_远程交互式控制.md":"nEgoiXFf","指南_框架必备_ruff代码检查.md":"DXNRTeJp","指南_框架必备_键鼠操作.md":"iAIG_Ugp","指南_简介_快速开始.md":"Cv7rF63a","指南_元素定位_去干扰识别.md":"B0Cc6Q-Q","指南_元素定位_属性定位.md":"CLIAW7gx","指南_特色功能_静态代码扫描.md":"DwAgtPWS","实践_dbus接口自动化测试_创建一条完整的用例.md":"DdTgoWxb","指南_元素定位_相对坐标定位.md":"DJVdtGyw","指南_框架必备_断言.md":"CEQjuwYR","实践_linux桌面ui自动化测试_初始化项目.md":"BQijfaJz"}
