{"实践_dbus接口自动化测试_初始化项目.md":"D1yRZaKw","指南_框架必备_测试报告.md":"CxOCzldc","指南_特色功能_wayland适配.md":"Dk47qe98","指南_特色功能_webui.md":"D6LW1LQQ","指南_特色功能_全自动日志.md":"Cf5pKvsL","指南_特色功能_失败录屏.md":"BdrwwXKK","指南_特色功能_数据回填.md":"CScL4WjB","指南_特色功能_标签化管理.md":"hv3xmnMH","指南_特色功能_标签自动同步.md":"BDizmX-t","指南_特色功能_重启类场景.md":"BeAJPDpt","指南_环境_环境部署.md":"DkEZLfCP","指南_环境_全局配置.md":"DYk-Aw_d","指南_特色功能_远程交互式控制.md":"BnLCZmwF","指南_简介_youqu是什么.md":"CWigO_4-","规划_未来规划.md":"Bziag6Sz","指南_简介_快速开始.md":"DhLUpfyy","规划_框架设计_at应用库设计方案.md":"untGwTXk","规划_框架设计_at基础框架设计方案.md":"BwauS4L0","规划_框架设计_自动化测试架构设计v1.0.md":"DcrAO-tt","实践_webui自动化测试_初始化项目.md":"DZxJWlna","指南_元素定位_去干扰识别.md":"BPfrRMuo","index.md":"03oZyAgl","实践_linux桌面ui自动化测试_远程交互式控制.md":"C_UNFwXa","实践_webui自动化测试_创建app工程.md":"DSJuQHhD","contributing.md":"Duu5eHNC","实践_http接口自动化测试_创建app工程.md":"CmeekBiF","实践_webui自动化测试_创建一条完整的用例.md":"C_ZiDXbZ","实践_dbus接口自动化测试_创建app工程.md":"Cp8jCc5Y","实践_dbus接口自动化测试_创建一条完整的用例.md":"BB8YT4Cw","实践_命令行自动化测试_初始化项目.md":"c9nv1-Ki","实践_命令行自动化测试_创建一条完整的用例.md":"DFsS6Xpr","sig.md":"CUJpEb6W","实践_linux桌面ui自动化测试_创建app工程.md":"BnIkM2IZ","实践_http接口自动化测试_初始化项目.md":"BEWvJAuD","指南_元素定位_ocr识别.md":"8b6cmYEM","实践_命令行自动化测试_创建app工程.md":"B6fe6Weo","实践_linux桌面ui自动化测试_创建一条完整的用例.md":"c4NkpIY4","实践_http接口自动化测试_创建一条完整的用例.md":"DpdPbLZe","指南_特色功能_标签导出.md":"BPeYgSq7","指南_框架必备_ruff代码检查.md":"BdaLye-v","指南_元素定位_相对坐标定位.md":"Cq31p1SO","指南_框架必备_执行管理器.md":"BYgl2Y6x","指南_框架必备_断言.md":"BFEuZF2o","指南_框架必备_键鼠操作.md":"sX0b_qrD","指南_元素定位_图像识别.md":"DtdCaFgO","实践_linux桌面ui自动化测试_初始化项目.md":"CboAixWX","release.md":"6zY2OgHZ","指南_元素定位_属性定位.md":"DuXo-RXe"}
